<?xml version="1.0" encoding="UTF-8"?>
<!DOCTYPE mapper PUBLIC "-//mybatis.org//DTD Mapper 3.0//EN" "http://mybatis.org/dtd/mybatis-3-mapper.dtd">

<mapper namespace="com.viotory.diary.mapper.GameMngMapper">

    <select id="selectGameListByMonth" resultType="com.viotory.diary.vo.GameVO">
        SELECT
            g.*,
            s.name AS stadiumName
        FROM games g
        LEFT JOIN stadiums s ON g.stadium_id = s.stadium_id -- 구장 테이블 조인
        WHERE DATE_FORMAT(g.game_date, '%Y-%m') = #{yearMonth}
        ORDER BY g.game_date ASC, g.game_time ASC
    </select>

    <select id="selectGameById" resultType="com.viotory.diary.vo.GameVO">
        SELECT * FROM games WHERE game_id = #{gameId}
    </select>

    <insert id="insertGame" parameterType="com.viotory.diary.vo.GameVO">
        INSERT INTO games (
            season, game_type, game_date, game_time, dh_code,
            stadium_id, home_team_code, away_team_code,
            score_home, score_away, winning_team,
            status, cancel_reason, home_starter, away_starter,
            etc_info, data_source, created_at
        )
        VALUES (
                   YEAR(#{gameDate}),      -- 날짜에서 연도 추출
                   'REGULAR',              -- 기본 정규시즌
                   #{gameDate},
                   #{gameTime},
                   '0',                    -- 기본 더블헤더 아님
                   #{stadiumId},
                   #{homeTeamCode},
                   #{awayTeamCode},
                   IFNULL(#{scoreHome}, 0),
                   IFNULL(#{scoreAway}, 0),
                   -- 승리팀 자동 계산 로직
                   CASE
                       WHEN #{status} = 'FINISHED' AND IFNULL(#{scoreHome},0) > IFNULL(#{scoreAway},0) THEN #{homeTeamCode}
                       WHEN #{status} = 'FINISHED' AND IFNULL(#{scoreAway},0) > IFNULL(#{scoreHome},0) THEN #{awayTeamCode}
                       WHEN #{status} = 'FINISHED' AND IFNULL(#{scoreHome},0) = IFNULL(#{scoreAway},0) THEN 'DRAW'
                       ELSE NULL
                       END,
                   #{status},
                   #{cancelReason},
                   #{homeStarter},
                   #{awayStarter},
                   #{etcInfo},
                   'MANUAL',               -- 수동 등록 명시
                   NOW()
               )
    </insert>

    <update id="updateGame" parameterType="com.viotory.diary.vo.GameVO">
        UPDATE games
        SET
            season         = YEAR(#{gameDate}), -- 날짜 변경 시 시즌도 같이 변경
            game_date      = #{gameDate},
            game_time      = #{gameTime},
            home_team_code = #{homeTeamCode},
            away_team_code = #{awayTeamCode},
            stadium_id     = #{stadiumId},
            score_home     = #{scoreHome},
            score_away     = #{scoreAway},
            -- 승리팀 재계산
            winning_team   = CASE
                                 WHEN #{status} = 'FINISHED' AND IFNULL(#{scoreHome},0) > IFNULL(#{scoreAway},0) THEN #{homeTeamCode}
                                 WHEN #{status} = 'FINISHED' AND IFNULL(#{scoreAway},0) > IFNULL(#{scoreHome},0) THEN #{awayTeamCode}
                                 WHEN #{status} = 'FINISHED' AND IFNULL(#{scoreHome},0) = IFNULL(#{scoreAway},0) THEN 'DRAW'
                                 ELSE NULL
                END,
            status         = #{status},
            etc_info       = #{etcInfo},
            home_starter   = #{homeStarter},
            away_starter   = #{awayStarter},
            cancel_reason  = #{cancelReason},
            updated_at     = NOW()
        WHERE game_id = #{gameId}
    </update>

    <delete id="deleteGame">
        DELETE FROM games WHERE game_id = #{gameId}
    </delete>

    <select id="selectStadiumList" resultType="com.viotory.diary.vo.StadiumVO">
        SELECT stadium_id, name
        FROM stadiums
        ORDER BY name ASC
    </select>

</mapper>